pyqt_custom_titlebar_setter/__init__.py
pyqt_custom_titlebar_setter/customTitlebarSetter.py
pyqt_custom_titlebar_setter-0.1.0.dist-info/LICENSE
pyqt_custom_titlebar_setter-0.1.0.dist-info/METADATA
pyqt_custom_titlebar_setter-0.1.0.dist-info/WHEEL
pyqt_custom_titlebar_setter-0.1.0.dist-info/top_level.txt
pyqt_custom_titlebar_setter-0.1.0.dist-info/RECORD
