Metadata-Version: 2.1
Name: pyqt-custom-titlebar-setter
Version: 0.1.0
Summary: PyQt custom titlebar setter (movable/resizable, etc.)
Home-page: https://github.com/yjg30737/pyqt-custom-titlebar-setter.git
Author: Jung Gyu Yoon
Author-email: yjg30737@gmail.com
License: MIT
License-File: LICENSE
Requires-Dist: PyQt5 >=5.15
Requires-Dist: pyqt-custom-titlebar-window
